coiote/__init__.py
coiote/auth.py
coiote/client.py
coiote/device_client.py
coiote/utils.py
coiote/v3/__init__.py
coiote/v3/access.py
coiote/v3/assigned_device_properties.py
coiote/v3/aws_integration.py
coiote/v3/cert_auth.py
coiote/v3/data_model.py
coiote/v3/device_events.py
coiote/v3/device_monitoring.py
coiote/v3/device_resources.py
coiote/v3/device_tests.py
coiote/v3/devices.py
coiote/v3/dialects.py
coiote/v3/domains.py
coiote/v3/extensions.py
coiote/v3/firmware_update.py
coiote/v3/groups.py
coiote/v3/lifecycle_management.py
coiote/v3/observations.py
coiote/v3/resources.py
coiote/v3/sessions.py
coiote/v3/setting_values.py
coiote/v3/task_reports.py
coiote/v3/task_templates.py
coiote/v3/tasks.py
coiote/v3/users.py
coiote/v3/model/__init__.py
coiote/v3/model/access.py
coiote/v3/model/assigned_device_properties.py
coiote/v3/model/aws_integration.py
coiote/v3/model/cert_auth.py
coiote/v3/model/data_model.py
coiote/v3/model/device_events.py
coiote/v3/model/device_monitoring.py
coiote/v3/model/device_resources.py
coiote/v3/model/device_tests.py
coiote/v3/model/devices.py
coiote/v3/model/dialects.py
coiote/v3/model/domains.py
coiote/v3/model/extensions.py
coiote/v3/model/firmware_update.py
coiote/v3/model/groups.py
coiote/v3/model/lifecycle_management.py
coiote/v3/model/observations.py
coiote/v3/model/resources.py
coiote/v3/model/setting_values.py
coiote/v3/model/task_reports.py
coiote/v3/model/task_templates.py
coiote/v3/model/tasks.py
coiote/v3/model/users.py
python_coiote-2.15.0.dist-info/LICENSE
python_coiote-2.15.0.dist-info/METADATA
python_coiote-2.15.0.dist-info/WHEEL
python_coiote-2.15.0.dist-info/top_level.txt
python_coiote-2.15.0.dist-info/RECORD
