Metadata-Version: 2.1
Name: python-coiote
Version: 2.15.0
Summary: Interact with Coiote DM API
Maintainer: Michał Grabowski
Maintainer-email: m.grabowski@avsystem.com
Classifier: Programming Language :: Python :: 3
Classifier: License :: OSI Approved :: MIT License
Classifier: Operating System :: OS Independent
Requires-Python: >=3.10
License-File: LICENSE
Requires-Dist: dacite~=1.8.1
Requires-Dist: python-dateutil~=2.8.2
Requires-Dist: pytz~=2022.7.1
Requires-Dist: requests~=2.31.0
Requires-Dist: tenacity~=8.2.3
Requires-Dist: typing-extensions~=4.9.0
